{
  "meta": {
    "year": 2024,
    "facility_type": "Hospital",
    "source_csv": "hospital_survey_2024.csv",
    "facility_id": "0001636",
    "facility_id_normalized": "0001636",
    "facility_name": "Morrison Community Hospital",
    "ahq_variant": "ahq-short",
    "beds_10_1_23": 25
  },
  "fields": {
    "id": "0001636",
    "hospital_name": "Morrison Community Hospital",
    "hospital_address": "303 N. Jackson St",
    "hospital_city": "Morrison",
    "zip": "61270",
    "fein_number": "36-6008167",
    "county": "Whiteside",
    "hsa": "1",
    "hpa": "B-03",
    "operator": "Morrison Community Hospital District",
    "plant_owner": "Morrison Community Hospital District",
    "hospital_type": "General Hospital",
    "hospital_certification": "Critical Access",
    "organization_type": "Government Hospital District",
    "other_org_details": "",
    "chna_report_link": "",
    "ems_management_contractor": "",
    "psychiatric_management_contractor": "",
    "rehab_management_contractor": "",
    "ms_con": "25",
    "icu_con": "0",
    "ped_con": "0",
    "obgyn_con": "0",
    "ltc_con": "0",
    "nnicu_con": "0",
    "rehab_con": "0",
    "ami_con": "0",
    "ltac_con": "0",
    "total_con": "25",
    "ms_0_14_admissions": "0",
    "ms_0_14_pd": "0",
    "ms_15_44_admissions": "6",
    "ms_15_44_pd": "21",
    "ms_45_64_admissions": "13",
    "ms_45_64_pd": "130",
    "ms_65_74_admissions": "38",
    "ms_65_74_pd": "417",
    "ms_75_admissions": "136",
    "ms_75_pd": "1,589",
    "ms_total_admissions": "193",
    "ms_total_pd": "2,157",
    "ms_beds_10_1_23": "25",
    "ms_peak_beds": "25",
    "ms_peak_daily_census": "18",
    "ms_observation_days": "667",
    "pediatric_admissions": "0",
    "pediatric_patient_days": "0",
    "pediatric_beds_set_up_10_1_23": "0",
    "pediatric_peak_beds": "0",
    "pediatric_peak_daily_census": "0",
    "pediatric_observation_days": "0",
    "direct_icu_admissions": "0",
    "direct_icu_patient_days": "0",
    "transferred_to_icu_admissions": "0",
    "transferred_to_icu_patient_days": "0",
    "total_icu_admissions": "0",
    "total_icu_patient_days": "0",
    "total_icu_beds_10_1_23": "0",
    "total_icu_peak_beds_set_up": "0",
    "total_icu_peak_daily_census": "0",
    "total_icu_observation_days": "0",
    "obstetrics_admissions": "0",
    "obstetrics_patient_days": "0",
    "clean_gynecology_admissions": "0",
    "cleangynecology_patient_days": "0",
    "total_ob_gyn_admissions": "0",
    "total_ob_gyn_patient_days": "0",
    "ob_gyn_beds_10_1_23": "0",
    "ob_gyn_peak_beds_set_up": "0",
    "ob_gyn_peak_daily_census": "0",
    "ob_gyn_observation_days": "0",
    "nn_icu_admissions": "0",
    "nn_icu_patient_days": "0",
    "nn_icu_beds_on_10_1_23": "0",
    "nn_icu_peak_beds": "0",
    "nn_icu_peak_daily_census": "0",
    "nn_icu_observation_days": "0",
    "ltc_admissions": "0",
    "ltc_patient_days": "0",
    "ltc_beds_10_1_23": "0",
    "ltc_peak_beds": "0",
    "ltc_peak_daily_census": "0",
    "ltc_observation_days": "0",
    "ltc_swing_bed_admissions": "0",
    "ltc_swing_bed_patient_days": "0",
    "ltc_swing_beds_peak_daily_census": "0",
    "ami_adolescent_admissions": "0",
    "ami_adolescent_patient_days": "0",
    "ami_adolescent_beds_on_10_1_23": "0",
    "ami_adolescent_peak_beds": "0",
    "ami_adolescent_peak_daily_census": "0",
    "ami_adolescent_observation_days": "0",
    "ami_adult_admissions": "0",
    "ami_adult_patient_days": "0",
    "ami_adult_beds_on_10_1_23": "0",
    "ami_adult_peak_beds": "0",
    "ami_adult_peak_daily_census": "0",
    "ami_adult_observation_days": "0",
    "total_ami_admissions": "0",
    "total_ami_patient_days": "0",
    "total_ami_beds_on_10_1_23": "0",
    "total_ami_observation_days": "0",
    "rehab_admissions": "0",
    "rehab_pd": "0",
    "rehab_beds_on_10_1_23": "0",
    "rehab_peak_beds": "0",
    "rehab_peak_daily_census": "0",
    "rehab_observation_days": "0",
    "ltac_admissions": "0",
    "ltac_patient_days": "0",
    "ltac_beds_on_10_1_23": "0",
    "ltac_peak_beds": "0",
    "ltac_peak_daily_census": "0",
    "ltac_observation_days": "0",
    "total_admissions": "193",
    "total_patient_days": "2,157",
    "total_beds_on_10_1_23": "25",
    "total_observation_days": "667",
    "dedicated_observation_beds": "0",
    "dedicated_observation_days": "0",
    "asian": "1",
    "asian_pd": "3",
    "native_american": "0",
    "native_american_pd": "0",
    "black": "0",
    "black_pd": "0",
    "pi_hawaiian": "0",
    "pi_hawaiian_pd": "0",
    "total": "193",
    "total_pd": "2,157",
    "white": "173",
    "white_pd": "1,957",
    "unknown_race": "19",
    "unknown_race_pd": "197",
    "hispanic_latino": "3",
    "hispanic_latino_pd": "20",
    "not_hispanic": "189",
    "not_hispanic_pd": "2,131",
    "ethnicity_unknown": "1",
    "ethnicity_unknown_pd": "6",
    "total_1": "193",
    "total_pd_1": "2,157",
    "outpatient_visits": "55,138",
    "outpatient_visits_off_site": "11,847",
    "total_outpatient_visits": "66,985",
    "inpatient_medicare": "154",
    "inpatient_medicaid": "4",
    "inpatient_other_public": "0",
    "inpatient_private_insurance": "15",
    "inpatient_private_payment": "20",
    "inpatient_total": "193",
    "inpatient_total_charity_care": "193",
    "outpatient_medicare": "22,720",
    "outpatient_medicaid": "11,490",
    "outpatient_other_public": "13",
    "outpatient_private_insurance": "31,389",
    "outpatient_private_payment": "1,160",
    "outpatient_total": "66,772",
    "outpatient_total_charity_care": "66,985",
    "inpatient_charity_care": "0",
    "outpatient_charity_care": "213",
    "cardio_ip_operating_rooms": "0",
    "cardio_op_operating_rooms": "0",
    "cardio_combined_room": "0",
    "cardio_total_operating_rooms": "0",
    "cardio_ip_surgical_cases": "0",
    "cardio_op_surgical_cases": "0",
    "cardio_ip_surgical_hours": "0",
    "cardio_op_surgical_hours": "0",
    "cardio_total_surgical_hours": "0",
    "dermatology_ip_operating_rooms": "0",
    "dermatology_op_operating_rooms": "0",
    "dermatology_combined_ors": "0",
    "total_dermatology_operating_rooms": "0",
    "dermatology_ip_surgical_cases": "0",
    "dermatology_op_surgical_cases": "0",
    "dermatology_ip_surgical_hours": "0",
    "dermatology_op_surgical_hours": "0",
    "dermatology_total_surgical_hours": "0",
    "general_ip_operating_rooms": "0",
    "general_op_operating_rooms": "0",
    "general_combined_operating_rooms": "3",
    "general_total_operating_rooms": "3",
    "general_ip_surgical_cases": "0",
    "general_op_surgical_cases": "190",
    "general_ip_surgical_hours": "0",
    "general_op_surgical_hours": "312",
    "general_total_surgical_hours": "312",
    "gastroenterology_ip_rooms": "0",
    "gastroenterology_op_rooms": "0",
    "gastro_combined_rooms": "0",
    "gastro_total_rooms": "0",
    "gastro_ip_surgical_cases": "0",
    "gastro_op_surgical_cases": "315",
    "gastro_ip_surgical_hours": "0",
    "gastro_op_surgical_hours": "272",
    "gastro_total_surgical_hours": "272",
    "neurology_ip_rooms": "0",
    "neurology_op_rooms": "0",
    "neurology_combined_rooms": "0",
    "neurology_total_rooms": "0",
    "neurology_ip_surgical_cases": "0",
    "neurology_op_surgical_cases": "0",
    "neurology_ip_surgical_hours": "0",
    "neurology_op_surgical_hours": "0",
    "neurology_total_surgical_hours": "0",
    "obgyn_ip_rooms": "0",
    "obgyn_op_rooms": "0",
    "obgyn_combined_rooms": "0",
    "obgyn_total_rooms": "0",
    "obgyn_ip_surgical_cases": "0",
    "obgyn_op_surgical_cases": "329",
    "obgyn_ip_surgical_hours": "0",
    "obgyn_op_surgical_hours": "622",
    "obgyn_total_surgical_hours": "622",
    "oral_ip_rooms": "0",
    "oral_op_rooms": "0",
    "oral_combined_rooms": "0",
    "oral_total_rooms": "0",
    "oral_ip_surgical_cases": "0",
    "oral_op_surgical_cases": "0",
    "oral_ip_surgical_hours": "0",
    "oral_op_surgical_hours": "0",
    "oral_total_surgical_hours": "0",
    "ophthalmology_ip_rooms": "0",
    "ophthalmology_op_rooms": "0",
    "ophthalmology_combined_rooms": "0",
    "ophthalmology_total_rooms": "0",
    "ophthalmology_ip_surgical_cases": "0",
    "ophthalmology_op_surgical_cases": "18",
    "ophthalmology_ip_surgical_hours": "0",
    "ophthalmology_op_surgical_hours": "13",
    "ophthalmology_total_surgical_hours": "13",
    "orthopedic_ip_rooms": "0",
    "orthopedic_op_rooms": "0",
    "orthopedic_combined_rooms": "0",
    "orthopedic_total_rooms": "0",
    "orthopedic_ip_surgical_cases": "0",
    "orthopedic_op_surgical_cases": "320",
    "orthopedic_ip_surgical_hours": "0",
    "orthopedic_op_surgical_hours": "706",
    "orthopedic_total_surgical_hours": "706",
    "otolarynhology_ip_rooms": "0",
    "otolarynhology_op_rooms": "0",
    "otolarynhology_combined_rooms": "0",
    "otolarynhology_total_rooms": "0",
    "otolarynhology_ip_surgical_cases": "0",
    "otolarynhology_op_surgical_cases": "273",
    "otolarynhology_ip_surgical_hours": "0",
    "otolarynhology_op_surgical_hours": "261",
    "otolarynhology_total_surgical_hours": "261",
    "plastic_ip_rooms": "0",
    "plastic_op_rooms": "0",
    "plastic_combined_rooms": "0",
    "plastic_total_rooms": "0",
    "plastic_ip_surgical_cases": "0",
    "plastic_op_surgical_cases": "0",
    "plastic_ip_surgical_hours": "0",
    "plastic_op_surgical_hours": "0",
    "plastic_total_surgical_hours": "0",
    "podiatry_ip_rooms": "0",
    "podiatry_op_rooms": "0",
    "podiatry_combined_rooms": "0",
    "podiatry_total_rooms": "0",
    "podiatry_ip_surgical_cases": "0",
    "podiatry_op_surgical_cases": "131",
    "podiatry_ip_surgical_hours": "0",
    "podiatry_op_surgical_hours": "219",
    "podiatry_total_surgical_hours": "219",
    "thoracic_ip_rooms": "0",
    "thoracic_op_rooms": "0",
    "thoracic_combined_rooms": "0",
    "thoracic_total_rooms": "0",
    "thoracic_ip_surgical_cases": "0",
    "thoracic_op_surgical_cases": "0",
    "thoracic_ip_surgical_hours": "0",
    "thoracic_op_surgical_hours": "0",
    "thoracic_total_surgical_hours": "0",
    "urology_ip_rooms": "0",
    "urology_op_rooms": "0",
    "urology_combined_rooms": "0",
    "urology_total_room": "0",
    "urology_ip_surgical_cases": "0",
    "urology_op_surgical_cases": "9",
    "urology_ip_surgical_hours": "0",
    "urology_op_surgical_hours": "12",
    "urology_total_surgical_hours": "12",
    "total_ip_operating_rooms": "0",
    "total_op_operating_rooms": "0",
    "total_combined_operating_rooms": "3",
    "total_operating_rooms": "3",
    "total_ip_surgical_cases": "0",
    "total_op_surgical_cases": "1,585",
    "total_ip_surgical_hours": "0",
    "total_op_surgical_hours": "2,417",
    "total_surgical_hours": "2,417",
    "gi_ip_rooms": "0",
    "gi_op_rooms": "0",
    "gi_combined_rooms": "0",
    "gi_total_rooms": "0",
    "gi_ip_cases": "0",
    "gi_op_cases": "0",
    "gi_ip_hours": "0",
    "gi_op_hours": "0",
    "gi_total_hours": "0",
    "laser_eye_ip_rooms": "0",
    "laser_eye_op_rooms": "0",
    "laser_eye_combined_rooms": "0",
    "laser_eye_total_rooms": "0",
    "laser_eye_ip_cases": "0",
    "laser_eye_op_cases": "0",
    "laser_eye_ip_hours": "0",
    "laser_eye_op_hours": "0",
    "laser_eye_total_hours": "0",
    "pain_ip_rooms": "0",
    "pain_op_rooms": "0",
    "pain_combined_rooms": "0",
    "pain_total_rooms": "0",
    "pain_ip_cases": "0",
    "pain_op_cases": "0",
    "pain_ip_hours": "0",
    "pain_op_hours": "0",
    "pain_total_hours": "0",
    "cystoscopy_ip_rooms": "0",
    "cystoscopy_op_rooms": "0",
    "cystoscopy_combined_rooms": "0",
    "cystoscopy_total_rooms": "0",
    "cystoscopy_ip_cases": "0",
    "cystoscopy_op_cases": "0",
    "cystoscopy_ip_hours": "0",
    "cystoscopy_op_hours": "0",
    "cystoscopy_total_hours": "0",
    "other_types_of_multipurpose_rooms": "Dermatology",
    "dp2_ipnum": "0",
    "dp2_opnum": "204",
    "dp2_iphrs": "0",
    "dp2_ophrs": "94",
    "dp2_tothrs": "94",
    "dproc3": "General Surgery",
    "dp3_ipnum": "0",
    "dp3_opnum": "365",
    "dp3_iphrs": "0",
    "dp3_ophrs": "253",
    "dp3_tothrs": "253",
    "dproc4": "Gynecology",
    "dp4_ipnum": "0",
    "dp4_opnum": "144",
    "dp4_iphrs": "0",
    "dp4_ophrs": "115",
    "dp4_tothrs": "115",
    "dproc5": "Neurology",
    "dp5_ipnum": "0",
    "dp5_opnum": "36",
    "dp5_iphrs": "0",
    "dp5_ophrs": "24",
    "dp5_tothrs": "24",
    "dproc6": "Podiatry",
    "dp6_ipnum": "0",
    "dp6_opnum": "956",
    "dp6_iphrs": "0",
    "dp6_ophrs": "400",
    "dp6_tothrs": "400",
    "dproc7": "Urology",
    "dp7_ipnum": "0",
    "dp7_opnum": "49",
    "dp7_iphrs": "0",
    "dp7_ophrs": "34",
    "dp7_tothrs": "34",
    "totalmultirooms": "6",
    "stage1rr": "3",
    "stage2rr": "6",
    "nlr": "0",
    "ndr": "0",
    "nbr": "0",
    "ldr": "0",
    "ldrp": "0",
    "delivery": "0",
    "livebirth": "0",
    "csection_rooms": "0",
    "csection_perf": "0",
    "level_i_beds": "0",
    "level_ii_beds": "0",
    "lev_1": "0",
    "lev_2": "0",
    "lev_2plus": "0",
    "orgtrans": "No",
    "heart": "0",
    "heart_lung": "0",
    "lung": "0",
    "kidney": "0",
    "liver": "0",
    "pancreas": "0",
    "cardsurg0_14": "0",
    "cardsurg15_over": "0",
    "cardsurgtotal": "0",
    "cabg": "0",
    "cardcathlabtotal": "0",
    "cardcathlabdiag": "0",
    "cardcathlabinter": "0",
    "cardcathlabep": "0",
    "cardcathlabmulti": "0",
    "cardcathdiag0_14": "0",
    "cardcathdiag15_over": "0",
    "cardcathinter0_14": "0",
    "cardcathinter15_over": "0",
    "cardcathep": "0",
    "totalcardcath": "0",
    "typeems": "Comprehensive",
    "erstations": "5",
    "ervisits": "4,495",
    "eradmissions": "272",
    "fsec_rooms": "0",
    "fsec_patients": "0",
    "fsec_admits": "0",
    "certtrauma": "No",
    "traumlvl1": "Off",
    "traumlvl2": "Off",
    "traumaroom": "0",
    "traumavisits": "0",
    "traumaadmit": "0",
    "iplabstudies": "28,027",
    "oplabstudies": "153,951",
    "conlabstudies": "16,025",
    "rfequip_hosp": "4",
    "rfequip_con": "0",
    "rfipx": "53",
    "rfopx": "6,395",
    "genradconipexam": "0",
    "genradconopexam": "0",
    "nucequip_hosp": "0",
    "nucequip_con": "0",
    "nucipx": "0",
    "nucopx": "0",
    "nuclconipexam": "0",
    "nuclconopexam": "0",
    "mamequip_hosp": "0",
    "mamequip_con": "1",
    "mamipx": "0",
    "mamopx": "0",
    "mamconipexam": "0",
    "mamconopexam": "675",
    "usequip_hosp": "3",
    "usequip_con": "0",
    "usipx": "10",
    "usopx": "2,077",
    "ultraconipexam": "0",
    "ultraconopexam": "0",
    "ct_scan_hosp": "1",
    "ct_scan_con": "0",
    "catipx": "21",
    "catopx": "2,337",
    "ctconipexam": "0",
    "ctconopexam": "0",
    "pethosp": "0",
    "petcon": "0",
    "petipx": "0",
    "petopx": "0",
    "petconipexam": "0",
    "petconopexam": "0",
    "mriho": "0",
    "contmri": "1",
    "mriipx": "0",
    "mriopx": "0",
    "mriconipexam": "1",
    "mriconopexam": "419",
    "angequip_hosp": "0",
    "angequip_con": "0",
    "diagangioip": "0",
    "diagangioop": "0",
    "condiagangioip": "0",
    "condiagangioop": "0",
    "interangioip": "0",
    "interangioop": "0",
    "coninterangioip": "0",
    "coninterangioop": "0",
    "hlitho": "0",
    "conlitho": "1",
    "lithoipx": "0",
    "linacceq_hosp": "0",
    "linacceq_con": "0",
    "linaccipexam": "0",
    "igrttreat": "0",
    "imrttreat": "0",
    "brachyhosp": "0",
    "brachycon": "0",
    "brachytreat": "0",
    "protonhosp": "0",
    "protoncont": "0",
    "protontreat": "0",
    "gammahosp": "0",
    "gammacont": "0",
    "gammatreat": "0",
    "cyberhosp": "0",
    "cybercont": "0",
    "cybertreat": "0",
    "equipcon1": "Mobile MRI",
    "eqcontractor1": "Central Illinois Imaging",
    "equipcon2": "3d Mammography Unit",
    "eqcontractor2": "Shared Services",
    "equipcon3": "Lithotripter",
    "eqcontractor3": "United Shockwave Services",
    "starting_date": "7/1/2023",
    "ending_date": "6/30/2024",
    "source_of_revenue_data": "Audited Financial Records",
    "total_capital_expenditures": " $-   ",
    "capital_expenditure_1": "3rd OR Completion",
    "capexp_obligated_1": "1631599",
    "capexp_financing_1": "Cash",
    "capexp_con_1": "",
    "capital_expenditure_2": "OR Department Renovation/Cafe Addition",
    "capexp_obligated_2": "1933350",
    "capexp_financing_2": "Cash",
    "capexp_con_2": "",
    "capital_expenditure_3": "Emr Installation",
    "capexp_obligated_3": "8743854",
    "capexp_financing_3": "Cash/Lease",
    "capexp_con_3": "",
    "capital_expenditure_4": "Administration Wing Renovation",
    "capexp_obligated_4": "845167",
    "capexp_financing_4": "Cash",
    "capexp_con_4": "",
    "capital_expenditure_5": "",
    "capexp_obligated_5": "0",
    "capexp_financing_5": "",
    "capexp_con_5": "",
    "capital_expenditure_6": "",
    "capexp_obligated_6": "0",
    "capexp_financing_6": "",
    "capexp_con_6": "",
    "capital_expenditure_7": "",
    "capexp_obligated_7": "0",
    "capexp_financing_7": "",
    "capexp_con_7": "",
    "capital_expenditure_8": "",
    "capexp_obligated_8": "0",
    "capexp_financing_8": "",
    "capexp_con_8": "",
    "capital_expenditure_9": "",
    "capexp_obligated_9": "0",
    "capexp_financing_9": "",
    "capexp_con_9": "",
    "capital_expenditure_10": "",
    "capexp_obligated_10": "0",
    "capexp_financing_10": "",
    "capexp_con_10": "",
    "capital_expenditure_11": "",
    "capexp_obligated_11": "0",
    "capexp_financing_11": "",
    "capexp_con_11": "",
    "capital_expenditure_12": "",
    "capexp_obligated_12": "0",
    "capexp_financing_12": "",
    "capexp_con_12": "",
    "capital_expenditure_13": "",
    "capexp_obligated_13": "0",
    "capexp_financing_13": "",
    "capexp_con_13": "",
    "inpatient_medicare_revenue": " $3,484,505 ",
    "inpatient_medicaid_revenue": " $26,647 ",
    "inpatient_other_public_revenue": " $-   ",
    "inpatient_private_insurance_revenue": " $168,449 ",
    "inpatient_private_payment_revenue": " $21,104 ",
    "total_inpat_revenue": " $3,700,705 ",
    "outpatient_medicare_revenue": " $18,621,364 ",
    "outpatient_medicaid_revenue": " $7,635,838 ",
    "outpatient_other_public_revenue": " $-   ",
    "outpatient_private_insurance_revenue": " $27,729,197 ",
    "outpatient_private_payment_revenue": " $681,358 ",
    "total_outpat_revenue": " $54,667,757 ",
    "actual_cost_charity_care_inpatient": " $2,229 ",
    "actual_cost_charity_care_outpatient": " $188,984 ",
    "fte_infection_control_staff": "0.7",
    "fte_infection_control_certified": "",
    "infection_control_contact": "Dominique Stout",
    "infection_control_telephone": "(815) 772-5567",
    "infection_control_email": "Dstout@mchstaff.com",
    "lactation_specialist": "No",
    "lact_spec_in_maternity": "Off",
    "trained_certified_lact_spec": "0",
    "board_certified_lact_spec": "0",
    "bi_mammography_equip": "1",
    "screening_mammograms": "540",
    "diagnostic_mammograms": "135",
    "bi_breast_ultrasound_equip": "2",
    "breast_ultrasounds": "178",
    "ultrasound_guided_breast_biopsies": "14",
    "bi_stereotactic_biopsy_equip": "0",
    "stereotactic_biopsies": "0",
    "bi_breast_mri_equip": "0",
    "breast_mris": "0",
    "no_breast_imaging_procedures": "Off",
    "covid": "",
    "administrator": "Pam J. Pfister",
    "administrator_s_job_title": "Chief Executive Officer",
    "administrator_phone": "(815) 772-5530",
    "administrator_email": "Ppfister@mchstaff.com",
    "contact_person": "Cami L. Megli",
    "contact_job_title": "Chief Financial Officer",
    "contact_phone": "(815) 772-5533",
    "contact_email": "Cmegli@mchstaff.com",
    "person_certifying": "Cami L. Megli",
    "certifier_job_title": "Chief Financial Officer",
    "certification_date": "4/4/2025",
    "helper": "",
    "comments": "",
    "hospital_organization": "",
    "contact_person_1": "",
    "contact_telephone": "",
    "contact_e_mail": "",
    "facility_diversity_comments": "",
    "planned_expenditures_female": "",
    "planned_expenditures_minority": "",
    "planned_expenditures_veteran": "",
    "planned_expenditures_small_business": "",
    "qualifyingcapitalexpenditures": "",
    "actualexpendituresfemale": "",
    "percent_expenditures_female": "",
    "actualexpendituresminority": "",
    "percent_expenditures_minority": "",
    "actualexpendituresveteran": "",
    "percent_expenditures_veteran": "",
    "actualexpendituressmallbusiness": "",
    "percent_expenditures_small_business": "",
    "planned_diversity_expenditures": "",
    "plan_for_diversity_recruitment": "",
    "challenges_to_diversity_recruitment": "",
    "hsfrb_assistance": "",
    "certifications": "",
    "point_of_contact": "",
    "enrollment_process": "",
    "examples_of_successes": "",
    "signature2": "",
    "full_address": "303 N. Jackson St, Morrison, IL 61270"
  },
  "raw": {
    "ID #": "0001636",
    "Hospital Name": "Morrison Community Hospital",
    "Hospital Address": "303 N. Jackson St",
    "Hospital City": "Morrison",
    "ZIP": "61270",
    "FEIN Number": "36-6008167",
    "County": "Whiteside",
    "HSA": "1",
    "HPA": "B-03",
    "Operator": "Morrison Community Hospital District",
    "Plant Owner": "Morrison Community Hospital District",
    "Hospital Type": "General Hospital",
    "Hospital Certification": "Critical Access",
    "Organization Type": "Government Hospital District",
    "Other Org Details": "",
    "CHNA Report Link": "",
    "EMS Management Contractor": "",
    "Psychiatric Management Contractor": "",
    "Rehab Management Contractor": "",
    "MS-CON": "25",
    "ICU-CON": "0",
    "PED-CON": "0",
    "OBGYN-CON": "0",
    "LTC-CON": "0",
    "NNICU-CON": "0",
    "REHAB-CON": "0",
    "AMI-CON": "0",
    "LTAC-CON": "0",
    "TOTAL-CON": "25",
    "MS 0-14 Admissions": "0",
    "MS 0-14 PD": "0",
    "MS 15-44 Admissions": "6",
    "MS 15-44 PD": "21",
    "MS 45-64 Admissions": "13",
    "MS 45-64 PD": "130",
    "MS 65-74 Admissions": "38",
    "MS 65-74 PD": "417",
    "MS 75+ Admissions": "136",
    "MS 75+ PD": "1,589",
    "MS Total Admissions": "193",
    "MS Total PD": "2,157",
    "MS Beds 10/1/23": "25",
    "MS Peak Beds": "25",
    "MS Peak Daily Census": "18",
    "MS Observation Days": "667",
    "Pediatric Admissions": "0",
    "Pediatric Patient Days": "0",
    "Pediatric Beds Set Up 10/1/23": "0",
    "Pediatric Peak Beds": "0",
    "Pediatric Peak Daily Census": "0",
    "Pediatric Observation Days": "0",
    "Direct ICU Admissions": "0",
    "Direct ICU Patient Days": "0",
    "Transferred to ICU Admissions": "0",
    "Transferred to ICU Patient Days": "0",
    "Total ICU Admissions": "0",
    "Total ICU Patient Days": "0",
    "Total ICU Beds 10/1/23": "0",
    "Total ICU Peak Beds Set Up": "0",
    "Total ICU Peak Daily Census": "0",
    "Total ICU Observation Days": "0",
    "Obstetrics Admissions": "0",
    "Obstetrics Patient Days": "0",
    "Clean Gynecology Admissions": "0",
    "CleanGynecology Patient Days": "0",
    "Total OB/GYN Admissions": "0",
    "Total OB/GYN Patient Days": "0",
    "OB/GYN beds 10/1/23": "0",
    "OB/GYN Peak Beds Set Up": "0",
    "OB/GYN Peak Daily Census": "0",
    "OB/GYN Observation Days": "0",
    "NN ICU Admissions": "0",
    "NN ICU Patient Days": "0",
    "NN ICU Beds on 10/1/23": "0",
    "NN ICU Peak Beds": "0",
    "NN ICU Peak Daily Census": "0",
    "NN ICU Observation Days": "0",
    "LTC Admissions": "0",
    "LTC Patient Days": "0",
    "LTC Beds 10/1/23": "0",
    "LTC Peak Beds": "0",
    "LTC Peak Daily Census": "0",
    "LTC Observation Days": "0",
    "LTC Swing Bed Admissions": "0",
    "LTC Swing Bed Patient Days": "0",
    "LTC Swing Beds Peak Daily Census": "0",
    "AMI Adolescent Admissions": "0",
    "AMI Adolescent Patient Days": "0",
    "AMI Adolescent Beds on 10/1/23": "0",
    "AMI Adolescent Peak Beds": "0",
    "AMI Adolescent Peak Daily Census": "0",
    "AMI Adolescent Observation Days": "0",
    "AMI Adult Admissions": "0",
    "AMI Adult Patient Days": "0",
    "AMI Adult Beds on 10/1/23": "0",
    "AMI Adult Peak Beds": "0",
    "AMI Adult Peak Daily Census": "0",
    "AMI Adult Observation Days": "0",
    "Total AMI Admissions": "0",
    "Total AMI Patient Days": "0",
    "Total AMI Beds on 10/1/23": "0",
    "Total AMI Observation Days": "0",
    "Rehab Admissions": "0",
    "Rehab PD": "0",
    "Rehab Beds on 10/1/23": "0",
    "Rehab Peak Beds": "0",
    "Rehab Peak Daily Census": "0",
    "Rehab Observation Days": "0",
    "LTAC Admissions": "0",
    "LTAC Patient Days": "0",
    "LTAC Beds on 10/1/23": "0",
    "LTAC Peak Beds": "0",
    "LTAC Peak Daily Census": "0",
    "LTAC Observation Days": "0",
    "Total Admissions": "193",
    "Total Patient Days": "2,157",
    "Total Beds on 10/1/23": "25",
    "Total Observation Days": "667",
    "Dedicated Observation Beds": "0",
    "Dedicated Observation Days": "0",
    "Asian": "1",
    "Asian PD": "3",
    "Native American": "0",
    "Native American PD": "0",
    "Black": "0",
    "Black PD": "0",
    "PI/Hawaiian": "0",
    "PI/Hawaiian PD": "0",
    "Total": "193",
    "Total PD": "2,157",
    "White": "173",
    "White PD": "1,957",
    "Unknown Race": "19",
    "Unknown Race PD": "197",
    "Hispanic/Latino": "3",
    "Hispanic/Latino PD": "20",
    "Not Hispanic": "189",
    "Not Hispanic PD": "2,131",
    "Ethnicity Unknown": "1",
    "Ethnicity Unknown PD": "6",
    "Total.1": "193",
    "Total PD.1": "2,157",
    "Outpatient Visits": "55,138",
    "Outpatient Visits off site": "11,847",
    "Total Outpatient Visits": "66,985",
    "Inpatient Medicare": "154",
    "Inpatient Medicaid": "4",
    "Inpatient Other Public": "0",
    "Inpatient Private Insurance": "15",
    "Inpatient Private Payment": "20",
    "Inpatient Total": "193",
    "Inpatient Total + Charity Care": "193",
    "Outpatient Medicare": "22,720",
    "Outpatient Medicaid": "11,490",
    "Outpatient Other Public": "13",
    "Outpatient Private Insurance": "31,389",
    "Outpatient Private Payment": "1,160",
    "Outpatient Total": "66,772",
    "Outpatient Total + Charity Care": "66,985",
    "Inpatient Charity Care": "0",
    "Outpatient Charity Care": "213",
    "Cardio IP Operating Rooms": "0",
    "Cardio OP Operating Rooms": "0",
    "Cardio Combined Room": "0",
    "Cardio Total Operating Rooms": "0",
    "Cardio IP Surgical Cases": "0",
    "Cardio OP Surgical Cases": "0",
    "Cardio IP Surgical Hours": "0",
    "Cardio OP Surgical Hours": "0",
    "Cardio Total Surgical Hours": "0",
    "Dermatology IP Operating Rooms": "0",
    "Dermatology OP Operating Rooms": "0",
    "Dermatology Combined Ors": "0",
    "Total Dermatology Operating Rooms": "0",
    "Dermatology IP Surgical Cases": "0",
    "Dermatology OP Surgical Cases": "0",
    "Dermatology IP Surgical Hours": "0",
    "Dermatology OP Surgical Hours": "0",
    "Dermatology Total Surgical Hours": "0",
    "General IP Operating Rooms": "0",
    "General OP Operating Rooms": "0",
    "General Combined Operating Rooms": "3",
    "General Total Operating Rooms": "3",
    "General IP Surgical Cases": "0",
    "General OP Surgical Cases": "190",
    "General IP Surgical Hours": "0",
    "General OP Surgical Hours": "312",
    "General Total Surgical Hours": "312",
    "Gastroenterology IP Rooms": "0",
    "Gastroenterology OP Rooms": "0",
    "Gastro Combined Rooms": "0",
    "Gastro Total Rooms": "0",
    "Gastro IP Surgical Cases": "0",
    "Gastro OP Surgical Cases": "315",
    "Gastro IP Surgical Hours": "0",
    "Gastro OP Surgical Hours": "272",
    "Gastro Total Surgical Hours": "272",
    "Neurology IP Rooms": "0",
    "Neurology OP Rooms": "0",
    "Neurology Combined Rooms": "0",
    "Neurology Total Rooms": "0",
    "Neurology IP Surgical Cases": "0",
    "Neurology OP Surgical Cases": "0",
    "Neurology IP Surgical Hours": "0",
    "Neurology OP Surgical Hours": "0",
    "Neurology Total Surgical Hours": "0",
    "OBGYN IP Rooms": "0",
    "OBGYN OP Rooms": "0",
    "OBGYN Combined Rooms": "0",
    "OBGYN Total Rooms": "0",
    "OBGYN IP Surgical Cases": "0",
    "OBGYN OP Surgical Cases": "329",
    "OBGYN IP Surgical Hours": "0",
    "OBGYN OP Surgical Hours": "622",
    "OBGYN Total Surgical Hours": "622",
    "Oral IP Rooms": "0",
    "Oral OP Rooms": "0",
    "Oral Combined Rooms": "0",
    "Oral Total Rooms": "0",
    "Oral IP Surgical Cases": "0",
    "Oral OP Surgical Cases": "0",
    "Oral IP Surgical Hours": "0",
    "Oral OP Surgical Hours": "0",
    "Oral Total Surgical Hours": "0",
    "Ophthalmology IP Rooms": "0",
    "Ophthalmology OP Rooms": "0",
    "Ophthalmology Combined Rooms": "0",
    "Ophthalmology Total Rooms": "0",
    "Ophthalmology IP Surgical Cases": "0",
    "Ophthalmology OP Surgical Cases": "18",
    "Ophthalmology IP Surgical Hours": "0",
    "Ophthalmology OP Surgical Hours": "13",
    "Ophthalmology Total Surgical Hours": "13",
    "Orthopedic IP Rooms": "0",
    "Orthopedic OP Rooms": "0",
    "Orthopedic Combined Rooms": "0",
    "Orthopedic Total Rooms": "0",
    "Orthopedic IP Surgical Cases": "0",
    "Orthopedic OP Surgical Cases": "320",
    "Orthopedic IP Surgical Hours": "0",
    "Orthopedic OP Surgical Hours": "706",
    "Orthopedic Total Surgical Hours": "706",
    "Otolarynhology IP Rooms": "0",
    "Otolarynhology OP Rooms": "0",
    "Otolarynhology Combined Rooms": "0",
    "Otolarynhology Total Rooms": "0",
    "Otolarynhology IP Surgical Cases": "0",
    "Otolarynhology OP Surgical Cases": "273",
    "Otolarynhology IP Surgical Hours": "0",
    "Otolarynhology OP Surgical Hours": "261",
    "Otolarynhology Total Surgical Hours": "261",
    "Plastic IP Rooms": "0",
    "Plastic OP Rooms": "0",
    "Plastic Combined Rooms": "0",
    "Plastic Total Rooms": "0",
    "Plastic IP Surgical Cases": "0",
    "Plastic OP Surgical Cases": "0",
    "Plastic IP Surgical Hours": "0",
    "Plastic OP Surgical Hours": "0",
    "Plastic Total Surgical Hours": "0",
    "Podiatry IP Rooms": "0",
    "Podiatry OP Rooms": "0",
    "Podiatry Combined Rooms": "0",
    "Podiatry Total Rooms": "0",
    "Podiatry IP Surgical Cases": "0",
    "Podiatry OP Surgical Cases": "131",
    "Podiatry IP Surgical Hours": "0",
    "Podiatry OP Surgical Hours": "219",
    "Podiatry Total Surgical Hours": "219",
    "Thoracic IP Rooms": "0",
    "Thoracic OP Rooms": "0",
    "Thoracic Combined Rooms": "0",
    "Thoracic Total Rooms": "0",
    "Thoracic IP Surgical Cases": "0",
    "Thoracic OP Surgical Cases": "0",
    "Thoracic IP Surgical Hours": "0",
    "Thoracic OP Surgical Hours": "0",
    "Thoracic Total Surgical Hours": "0",
    "Urology IP Rooms": "0",
    "Urology OP Rooms": "0",
    "Urology Combined Rooms": "0",
    "Urology Total Room": "0",
    "Urology IP Surgical Cases": "0",
    "Urology OP Surgical Cases": "9",
    "Urology IP Surgical Hours": "0",
    "Urology OP Surgical Hours": "12",
    "Urology Total Surgical Hours": "12",
    "Total IP Operating Rooms": "0",
    "Total OP Operating Rooms": "0",
    "Total Combined Operating Rooms": "3",
    "Total Operating Rooms": "3",
    "Total IP Surgical Cases": "0",
    "Total OP Surgical Cases": "1,585",
    "Total IP Surgical Hours": "0",
    "Total OP Surgical Hours": "2,417",
    "Total Surgical Hours": "2,417",
    "GI IP Rooms": "0",
    "GI OP Rooms": "0",
    "GI Combined Rooms": "0",
    "GI Total Rooms": "0",
    "GI IP Cases": "0",
    "GI OP Cases": "0",
    "GI IP Hours": "0",
    "GI OP Hours": "0",
    "GI Total Hours": "0",
    "Laser Eye IP Rooms": "0",
    "Laser Eye OP Rooms": "0",
    "Laser Eye Combined Rooms": "0",
    "Laser Eye Total Rooms": "0",
    "Laser Eye IP Cases": "0",
    "Laser Eye OP Cases": "0",
    "Laser Eye IP Hours": "0",
    "Laser Eye OP Hours": "0",
    "Laser Eye Total Hours": "0",
    "Pain IP Rooms": "0",
    "Pain OP Rooms": "0",
    "Pain Combined Rooms": "0",
    "Pain Total Rooms": "0",
    "Pain IP Cases": "0",
    "Pain OP Cases": "0",
    "Pain IP Hours": "0",
    "Pain OP Hours": "0",
    "Pain Total Hours": "0",
    "Cystoscopy IP Rooms": "0",
    "Cystoscopy OP Rooms": "0",
    "Cystoscopy Combined Rooms": "0",
    "Cystoscopy Total Rooms": "0",
    "Cystoscopy IP Cases": "0",
    "Cystoscopy OP Cases": "0",
    "Cystoscopy IP hours": "0",
    "Cystoscopy OP hours": "0",
    "Cystoscopy Total hours": "0",
    "Other Types of Multipurpose rooms": "Dermatology",
    "dp2_ipnum": "0",
    "dp2_opnum": "204",
    "dp2_iphrs": "0",
    "dp2_ophrs": "94",
    "dp2_tothrs": "94",
    "dproc3": "General Surgery",
    "dp3_ipnum": "0",
    "dp3_opnum": "365",
    "dp3_iphrs": "0",
    "dp3_ophrs": "253",
    "dp3_tothrs": "253",
    "dproc4": "Gynecology",
    "dp4_ipnum": "0",
    "dp4_opnum": "144",
    "dp4_iphrs": "0",
    "dp4_ophrs": "115",
    "dp4_tothrs": "115",
    "dproc5": "Neurology",
    "dp5_ipnum": "0",
    "dp5_opnum": "36",
    "dp5_iphrs": "0",
    "dp5_ophrs": "24",
    "dp5_tothrs": "24",
    "dproc6": "Podiatry",
    "dp6_ipnum": "0",
    "dp6_opnum": "956",
    "dp6_iphrs": "0",
    "dp6_ophrs": "400",
    "dp6_tothrs": "400",
    "dproc7": "Urology",
    "dp7_ipnum": "0",
    "dp7_opnum": "49",
    "dp7_iphrs": "0",
    "dp7_ophrs": "34",
    "dp7_tothrs": "34",
    "TotalMultiRooms": "6",
    "stage1rr": "3",
    "stage2rr": "6",
    "nlr": "0",
    "ndr": "0",
    "nbr": "0",
    "ldr": "0",
    "ldrp": "0",
    "delivery": "0",
    "livebirth": "0",
    "CSection_Rooms": "0",
    "CSection_Perf": "0",
    "Level I Beds": "0",
    "Level II Beds": "0",
    "Level II+ Beds": "0",
    "lev_1": "0",
    "lev_2": "0",
    "lev_2plus": "0",
    "orgtrans": "No",
    "heart": "0",
    "heart/lung": "0",
    "lung": "0",
    "kidney": "0",
    "liver": "0",
    "pancreas": "0",
    "CardSurg0_14": "0",
    "CardSurg15_Over": "0",
    "CardSurgTotal": "0",
    "CABG": "0",
    "CardCathLabTotal": "0",
    "CardCathLabDiag": "0",
    "CardCathLabInter": "0",
    "CardCathLabEP": "0",
    "CardCathLabMulti": "0",
    "CardCathDiag0_14": "0",
    "CardCathDiag15_Over": "0",
    "CardCathInter0_14": "0",
    "CardCathInter15_Over": "0",
    "CardCathEP": "0",
    "TotalCardCath": "0",
    "typeems": "Comprehensive",
    "ERstations": "5",
    "ERvisits": "4,495",
    "ERadmissions": "272",
    "FSEC Rooms": "0",
    "FSEC Patients": "0",
    "FSEC Admits": "0",
    "CertTrauma": "No",
    "TraumLvl1": "Off",
    "TraumLvl2": "Off",
    "traumaroom": "0",
    "TraumaVisits": "0",
    "TraumaAdmit": "0",
    "IPLabStudies": "28,027",
    "OPLabStudies": "153,951",
    "ConLabStudies": "16,025",
    "rfequip_hosp": "4",
    "rfequip_con": "0",
    "rfipx": "53",
    "rfopx": "6,395",
    "GenRadConIPExam": "0",
    "GenRadConOPExam": "0",
    "nucequip_hosp": "0",
    "nucequip_con": "0",
    "nucipx": "0",
    "nucopx": "0",
    "NuclConIPExam": "0",
    "NuclConOPExam": "0",
    "mamequip_hosp": "0",
    "mamequip_con": "1",
    "mamipx": "0",
    "mamopx": "0",
    "MamConIPExam": "0",
    "MamConOPExam": "675",
    "usequip_hosp": "3",
    "usequip_con": "0",
    "usipx": "10",
    "usopx": "2,077",
    "UltraConIPExam": "0",
    "UltraConOPExam": "0",
    "ct_scan_hosp": "1",
    "ct_scan_con": "0",
    "catipx": "21",
    "catopx": "2,337",
    "CTConIPExam": "0",
    "CTConOPExam": "0",
    "pethosp": "0",
    "petcon": "0",
    "petipx": "0",
    "petopx": "0",
    "PETConIPExam": "0",
    "PETConOPExam": "0",
    "mriho": "0",
    "contmri": "1",
    "mriipx": "0",
    "mriopx": "0",
    "MRIConIPExam": "1",
    "MRIConOPExam": "419",
    "angequip_hosp": "0",
    "angequip_con": "0",
    "DiagAngioIP": "0",
    "DiagAngioOP": "0",
    "ConDiagAngioIP": "0",
    "ConDiagAngioOP": "0",
    "InterAngioIP": "0",
    "InterAngioOP": "0",
    "ConInterAngioIP": "0",
    "ConInterAngioOP": "0",
    "hlitho": "0",
    "conlitho": "1",
    "lithoipx": "0",
    "LinAccEq_hosp": "0",
    "LinAccEq_con": "0",
    "LinAccIPExam": "0",
    "IGRTtreat": "0",
    "IMRTtreat": "0",
    "BrachyHosp": "0",
    "BrachyCon": "0",
    "BrachyTreat": "0",
    "ProtonHosp": "0",
    "ProtonCont": "0",
    "ProtonTreat": "0",
    "GammaHosp": "0",
    "GammaCont": "0",
    "GammaTreat": "0",
    "CyberHosp": "0",
    "CyberCont": "0",
    "CyberTreat": "0",
    "EquipCon1": "Mobile MRI",
    "EqContractor1": "Central Illinois Imaging",
    "EquipCon2": "3d Mammography Unit",
    "EqContractor2": "Shared Services",
    "EquipCon3": "Lithotripter",
    "EqContractor3": "United Shockwave Services",
    "Starting Date": "7/1/2023",
    "Ending Date": "6/30/2024",
    "Source of Revenue Data": "Audited Financial Records",
    " Total Capital Expenditures ": " $-   ",
    "Capital Expenditure 1": "3rd OR Completion",
    "CapExp Obligated 1": "1631599",
    "CapExp Financing 1": "Cash",
    "CapExp CON 1": "",
    "Capital Expenditure 2": "OR Department Renovation/Cafe Addition",
    "CapExp Obligated 2": "1933350",
    "CapExp Financing 2": "Cash",
    "CapExp CON 2": "",
    "Capital Expenditure 3": "Emr Installation",
    "CapExp Obligated 3": "8743854",
    "CapExp Financing 3": "Cash/Lease",
    "CapExp CON 3": "",
    "Capital Expenditure 4": "Administration Wing Renovation",
    "CapExp Obligated 4": "845167",
    "CapExp Financing 4": "Cash",
    "CapExp CON 4": "",
    "Capital Expenditure 5": "",
    "CapExp Obligated 5": "0",
    "CapExp Financing 5": "",
    "CapExp CON 5": "",
    "Capital Expenditure 6": "",
    "CapExp Obligated 6": "0",
    "CapExp Financing 6": "",
    "CapExp CON 6": "",
    "Capital Expenditure 7": "",
    "CapExp Obligated 7": "0",
    "CapExp Financing 7": "",
    "CapExp CON 7": "",
    "Capital Expenditure 8": "",
    "CapExp Obligated 8": "0",
    "CapExp Financing 8": "",
    "CapExp CON 8": "",
    "Capital Expenditure 9": "",
    "CapExp Obligated 9": "0",
    "CapExp Financing 9": "",
    "CapExp CON 9": "",
    "Capital Expenditure 10": "",
    "CapExp Obligated 10": "0",
    "CapExp Financing 10": "",
    "CapExp CON 10": "",
    "Capital Expenditure 11": "",
    "CapExp Obligated 11": "0",
    "CapExp Financing 11": "",
    "CapExp CON 11": "",
    "Capital Expenditure 12": "",
    "CapExp Obligated 12": "0",
    "CapExp Financing 12": "",
    "CapExp CON 12": "",
    "Capital Expenditure 13": "",
    "CapExp Obligated 13": "0",
    "CapExp Financing 13": "",
    "CapExp CON 13": "",
    " Inpatient Medicare Revenue ": " $3,484,505 ",
    " Inpatient Medicaid Revenue ": " $26,647 ",
    " Inpatient Other Public Revenue ": " $-   ",
    " Inpatient Private Insurance Revenue ": " $168,449 ",
    " Inpatient Private Payment Revenue ": " $21,104 ",
    " Total Inpat Revenue ": " $3,700,705 ",
    " Outpatient Medicare Revenue ": " $18,621,364 ",
    " Outpatient Medicaid Revenue ": " $7,635,838 ",
    " Outpatient Other Public Revenue ": " $-   ",
    " Outpatient Private Insurance Revenue ": " $27,729,197 ",
    " Outpatient Private Payment Revenue ": " $681,358 ",
    " Total Outpat Revenue ": " $54,667,757 ",
    " Actual Cost Charity Care Inpatient ": " $2,229 ",
    " Actual Cost Charity Care Outpatient ": " $188,984 ",
    "FTE Infection Control Staff": "0.7",
    "FTE Infection Control Certified": "",
    "Infection Control Contact": "Dominique Stout",
    "Infection Control Telephone": "(815) 772-5567",
    "Infection Control Email": "Dstout@mchstaff.com",
    "Lactation Specialist": "No",
    "Lact Spec in Maternity": "Off",
    "Trained Certified Lact Spec": "0",
    "Board Certified Lact Spec": "0",
    "BI Mammography Equip": "1",
    "Screening Mammograms": "540",
    "Diagnostic Mammograms": "135",
    "BI Breast Ultrasound Equip": "2",
    "Breast Ultrasounds": "178",
    "Ultrasound Guided Breast Biopsies": "14",
    "BI Stereotactic Biopsy Equip": "0",
    "Stereotactic Biopsies": "0",
    "BI Breast MRI Equip": "0",
    "Breast MRIs": "0",
    "No Breast Imaging Procedures": "Off",
    "Covid": "",
    "Administrator": "Pam J. Pfister",
    "Administrator's Job Title": "Chief Executive Officer",
    "Administrator Phone": "(815) 772-5530",
    "Administrator Email": "Ppfister@mchstaff.com",
    "Contact Person": "Cami L. Megli",
    "Contact Job Title": "Chief Financial Officer",
    "Contact Phone": "(815) 772-5533",
    "Contact Email": "Cmegli@mchstaff.com",
    "Person Certifying": "Cami L. Megli",
    "Certifier Job Title": "Chief Financial Officer",
    "Certification Date": "4/4/2025",
    "helper": "",
    "comments": "",
    "Hospital - Organization": "",
    "Contact Person.1": "",
    "Contact Telephone": "",
    "Contact E-Mail": "",
    "Facility Diversity Comments": "",
    "Planned Expenditures Female": "",
    "Planned Expenditures Minority": "",
    "Planned Expenditures Veteran": "",
    "Planned Expenditures Small Business": "",
    "QualifyingCapitalExpenditures": "",
    "ActualExpendituresFemale": "",
    "Percent Expenditures Female": "",
    "ActualExpendituresMinority": "",
    "Percent Expenditures Minority": "",
    "ActualExpendituresVeteran": "",
    "Percent Expenditures Veteran": "",
    "ActualExpendituresSmallBusiness": "",
    "Percent Expenditures Small Business": "",
    "Planned Diversity Expenditures": "",
    "Plan for Diversity Recruitment": "",
    "Challenges to Diversity Recruitment": "",
    "HSFRB Assistance": "",
    "Certifications": "",
    "Point of Contact": "",
    "Enrollment Process": "",
    "Examples of Successes": "",
    "Signature2": "",
    "Full Address": "303 N. Jackson St, Morrison, IL 61270"
  }
}
